pybancodobrasil/__init__.py
pybancodobrasil-0.2.1.dist-info/WHEEL
pybancodobrasil-0.2.1.dist-info/METADATA
pybancodobrasil-0.2.1.dist-info/RECORD
