Metadata-Version: 2.1
Name: pybancodobrasil
Version: 0.2.1
Summary: This module do web crawler of banco do brasil.
Home-page: https://github.com/guifabrin/pybancodobrasil
Author: Guilherme Fabrin Franco
Author-email: guilherme.fabrin@gmail.com
Classifier: Development Status :: 4 - Beta
Classifier: Programming Language :: Python
Classifier: License :: OSI Approved :: MIT License
Classifier: Topic :: Software Development :: Libraries :: Python Modules
Classifier: Programming Language :: Python :: 3
Classifier: Programming Language :: Python :: 3.6
Classifier: Programming Language :: Python :: 3.7
Classifier: Programming Language :: Python :: 3.8
Classifier: Programming Language :: Python :: 3.9
